README.txt
setup.py
Products/__init__.py
Products.UpfrontContacts.egg-info/PKG-INFO
Products.UpfrontContacts.egg-info/SOURCES.txt
Products.UpfrontContacts.egg-info/dependency_links.txt
Products.UpfrontContacts.egg-info/entry_points.txt
Products.UpfrontContacts.egg-info/namespace_packages.txt
Products.UpfrontContacts.egg-info/not-zip-safe
Products.UpfrontContacts.egg-info/requires.txt
Products.UpfrontContacts.egg-info/top_level.txt
Products/UpfrontContacts/CHANGES.txt
Products/UpfrontContacts/ContactManager.py
Products/UpfrontContacts/CustomFields.py
Products/UpfrontContacts/LICENSE.GPL
Products/UpfrontContacts/NOTES.txt
Products/UpfrontContacts/Organisation.py
Products/UpfrontContacts/Person.py
Products/UpfrontContacts/README.TXT
Products/UpfrontContacts/TODO.txt
Products/UpfrontContacts/UpfrontContactsTool.py
Products/UpfrontContacts/__init__.py
Products/UpfrontContacts/config.py
Products/UpfrontContacts/configure.zcml
Products/UpfrontContacts/interfaces.py
Products/UpfrontContacts/organisation_schema.py
Products/UpfrontContacts/person_schema.py
Products/UpfrontContacts/references.py
Products/UpfrontContacts/schemapatch.py
Products/UpfrontContacts/tool.gif
Products/UpfrontContacts/utils.py
Products/UpfrontContacts/version.txt
Products/UpfrontContacts/Extensions/Install.py
Products/UpfrontContacts/browser/__init__.py
Products/UpfrontContacts/browser/configure.zcml
Products/UpfrontContacts/browser/contact.py
Products/UpfrontContacts/browser/contacttools.pt
Products/UpfrontContacts/debian/changelog
Products/UpfrontContacts/debian/compat
Products/UpfrontContacts/debian/control
Products/UpfrontContacts/debian/copyright
Products/UpfrontContacts/debian/dzproduct
Products/UpfrontContacts/debian/postinst
Products/UpfrontContacts/debian/rules
Products/UpfrontContacts/profiles/default/portlets.xml
Products/UpfrontContacts/skins/upfrontcontacts/add_person.py
Products/UpfrontContacts/skins/upfrontcontacts/constructBatch.py
Products/UpfrontContacts/skins/upfrontcontacts/contactmanager.png
Products/UpfrontContacts/skins/upfrontcontacts/contactmanager_view.pt
Products/UpfrontContacts/skins/upfrontcontacts/custom_address_widget.pt
Products/UpfrontContacts/skins/upfrontcontacts/email_widget.pt
Products/UpfrontContacts/skins/upfrontcontacts/get_companies_and_people.py
Products/UpfrontContacts/skins/upfrontcontacts/make_vcard.py
