Metadata-Version: 1.0
Name: Products.UpfrontContacts
Version: 0.6
Summary: Manage organisations, people and the relationships between them inside Plone and allow them to log in easily to your Plone site.
Home-page: UNKNOWN
Author: RC Compaan
Author-email: roche at upfrontsystems dot co dot za
License: GPL
Keywords: contacts addressbook addresses
Platform: UNKNOWN
Classifier: Programming Language :: Python
